nonebot_plugin_rauthman/__init__.py
nonebot_plugin_rauthman-2.0.0a13.dist-info/LICENSE
nonebot_plugin_rauthman-2.0.0a13.dist-info/WHEEL
nonebot_plugin_rauthman-2.0.0a13.dist-info/METADATA
nonebot_plugin_rauthman-2.0.0a13.dist-info/RECORD
