Metadata-Version: 2.1
Name: nonebot-plugin-rauthman
Version: 2.0.0a13
Summary: Rule-based authorization manager worked with nonebot2
Home-page: https://github.com/Lancercmd/nonebot_plugin_rauthman
License: GPLv3
Author: Lancercmd
Author-email: lancercmd@gmail.com
Requires-Python: >=3.8,<4.0
Classifier: License :: Other/Proprietary License
Classifier: Programming Language :: Python :: 3
Classifier: Programming Language :: Python :: 3.8
Classifier: Programming Language :: Python :: 3.9
Requires-Dist: nonebot-adapter-cqhttp (>=2.0.0-alpha.13,<3.0.0)
Requires-Dist: nonebot2 (>=2.0.0-alpha.13,<3.0.0)
Requires-Dist: ujson (>=4.0.2,<5.0.0)
Project-URL: Repository, https://github.com/Lancercmd/nonebot_plugin_rauthman
